basset_client/__init__.py
basset_client/assets.py
basset_client/basset.py
basset_client/client.py
basset_client/generate_hash.py
basset_client/git.py
basset_python_client-1.0.0b0.dist-info/LICENSE
basset_python_client-1.0.0b0.dist-info/METADATA
basset_python_client-1.0.0b0.dist-info/WHEEL
basset_python_client-1.0.0b0.dist-info/top_level.txt
basset_python_client-1.0.0b0.dist-info/RECORD
