Metadata-Version: 2.1
Name: basset-python-client
Version: 1.0.0b0
Summary: Python client for submitting snapshots to basset
Home-page: https://basset.io
Author: Jeremy Gonzalez
Author-email: jeremy@jeremyg.net
License: MIT
Project-URL: Source Code, https://github.com/basset/python-client
Platform: UNKNOWN
